[{"name":"Ivan","age":24},{"name":"Kseniya","age":40},{"name":"Natasha","age":27},{"name":"Natasha","age":21},{"name":"Natasha","age":21},{"name":"Andrey","age":43},{"name":"Ivan","age":39},{"name":"Masha","age":21},{"name":"Natasha","age":24},{"name":"Masha","age":28},{"name":"Kseniya","age":32},{"name":"Kseniya","age":45},{"name":"Natasha","age":33},{"name":"Kseniya","age":33},{"name":"Masha","age":29},{"name":"Natasha","age":25},{"name":"Natasha","age":37},{"name":"Ivan","age":27},{"name":"Andrey","age":24},{"name":"Masha","age":22},{"name":"Masha","age":42},{"name":"Andrey","age":35},{"name":"Kseniya","age":41},{"name":"Ivan","age":33},{"name":"Kseniya","age":40},{"name":"Natasha","age":40},{"name":"Kseniya","age":23},{"name":"Kseniya","age":18},{"name":"Natasha","age":42},{"name":"Andrey","age":37},{"name":"Andrey","age":30},{"name":"Ivan","age":27},{"name":"Kseniya","age":36},{"name":"Natasha","age":23},{"name":"Andrey","age":25},{"name":"Kseniya","age":39},{"name":"Ivan","age":21},{"name":"Natasha","age":20},{"name":"Masha","age":28},{"name":"Andrey","age":44},{"name":"Natasha","age":24},{"name":"Masha","age":22},{"name":"Andrey","age":27},{"name":"Masha","age":37},{"name":"Kseniya","age":37},{"name":"Ivan","age":22},{"name":"Natasha","age":27},{"name":"Ivan","age":25},{"name":"Natasha","age":45},{"name":"Masha","age":39}]